pixelgraph/__init__.py
pixelgraph/callback.py
pixelgraph/cli.py
pixelgraph/server.py
pixelgraph/schemas/__init__.py
pixelgraph/schemas/events.py
pixelgraph/static/index.html
pixelgraph/static/assets/index-BoARAmk4.js
pixelgraph/static/assets/index-DQy_14IR.css
pixelgraph/static/assets/sprites/wizard.svg
pixelgraph-0.1.0.dist-info/licenses/LICENSE
pixelgraph-0.1.0.dist-info/METADATA
pixelgraph-0.1.0.dist-info/WHEEL
pixelgraph-0.1.0.dist-info/entry_points.txt
pixelgraph-0.1.0.dist-info/top_level.txt
pixelgraph-0.1.0.dist-info/RECORD
