Metadata-Version: 2.4
Name: pixelgraph
Version: 0.1.0
Summary: 8-bit visualization for LangGraph agents
Author-email: Diego <diego@example.com>
License: MIT
Project-URL: Homepage, https://github.com/diegonov1/PixelGraph
Project-URL: Repository, https://github.com/diegonov1/PixelGraph
Project-URL: Issues, https://github.com/diegonov1/PixelGraph/issues
Keywords: langgraph,langchain,visualization,8-bit,agents,ai
Classifier: Development Status :: 3 - Alpha
Classifier: Intended Audience :: Developers
Classifier: License :: OSI Approved :: MIT License
Classifier: Programming Language :: Python :: 3
Classifier: Programming Language :: Python :: 3.10
Classifier: Programming Language :: Python :: 3.11
Classifier: Programming Language :: Python :: 3.12
Classifier: Topic :: Scientific/Engineering :: Artificial Intelligence
Requires-Python: >=3.10
License-File: LICENSE
Requires-Dist: fastapi>=0.104.0
Requires-Dist: uvicorn[standard]>=0.24.0
Requires-Dist: pydantic>=2.0.0
Requires-Dist: websockets>=12.0
Requires-Dist: langchain-core>=0.1.0
Provides-Extra: dev
Requires-Dist: pytest>=7.4.0; extra == "dev"
Requires-Dist: pytest-asyncio>=0.21.0; extra == "dev"
Requires-Dist: httpx>=0.25.0; extra == "dev"
Requires-Dist: black>=23.0.0; extra == "dev"
Requires-Dist: mypy>=1.0.0; extra == "dev"
Provides-Extra: langgraph
Requires-Dist: langgraph>=0.0.40; extra == "langgraph"
Provides-Extra: openai
Requires-Dist: langchain-openai>=0.0.5; extra == "openai"
Provides-Extra: all
Requires-Dist: pixelgraph[dev,langgraph,openai]; extra == "all"
Dynamic: license-file
